{
  "ExpressionLimit": {"Type": "All"},
  "CollapseSettings": {
    "CollapseType": "ERA",
    "EraPad": 30
  },
  "CensorWindow": {
    "StartDate": null,
    "EndDate": null
  },
  "ConceptSets": [
    {
      "expression": {"items": [{
        "isExcluded": false,
        "concept": {
          "INVALID_REASON_CAPTION": "Valid",
          "CONCEPT_ID": 80502,
          "STANDARD_CONCEPT": "S",
          "CONCEPT_CODE": "64859006",
          "VOCABULARY_ID": "SNOMED",
          "CONCEPT_NAME": "Osteoporosis",
          "DOMAIN_ID": "Condition",
          "STANDARD_CONCEPT_CAPTION": "Standard",
          "CONCEPT_CLASS_ID": "Clinical Finding",
          "INVALID_REASON": "V"
        },
        "includeMapped": false,
        "includeDescendants": true
      }]},
      "name": "Osteoporosis",
      "id": 0
    },
    {
      "expression": {"items": [{
        "isExcluded": false,
        "concept": {
          "INVALID_REASON_CAPTION": "Valid",
          "CONCEPT_ID": 1512480,
          "STANDARD_CONCEPT": "S",
          "CONCEPT_CODE": "115264",
          "VOCABULARY_ID": "RxNorm",
          "CONCEPT_NAME": "Ibandronate",
          "DOMAIN_ID": "Drug",
          "STANDARD_CONCEPT_CAPTION": "Standard",
          "CONCEPT_CLASS_ID": "Ingredient",
          "INVALID_REASON": "V"
        },
        "includeMapped": false,
        "includeDescendants": true
      }]},
      "name": "Ibandronate",
      "id": 1
    },
    {
      "expression": {"items": [{
        "isExcluded": false,
        "concept": {
          "INVALID_REASON_CAPTION": "Valid",
          "CONCEPT_ID": 1557272,
          "STANDARD_CONCEPT": "S",
          "CONCEPT_CODE": "46041",
          "VOCABULARY_ID": "RxNorm",
          "CONCEPT_NAME": "Alendronate",
          "DOMAIN_ID": "Drug",
          "STANDARD_CONCEPT_CAPTION": "Standard",
          "CONCEPT_CLASS_ID": "Ingredient",
          "INVALID_REASON": "V"
        },
        "includeMapped": false,
        "includeDescendants": true
      }]},
      "name": "Alendronate",
      "id": 2
    },
    {
      "expression": {"items": [{
        "isExcluded": false,
        "concept": {
          "INVALID_REASON_CAPTION": "Valid",
          "CONCEPT_ID": 36211099,
          "STANDARD_CONCEPT": "C",
          "CONCEPT_CODE": "10016454",
          "VOCABULARY_ID": "MedDRA",
          "CONCEPT_NAME": "Femur fracture",
          "DOMAIN_ID": "Condition",
          "STANDARD_CONCEPT_CAPTION": "Classification",
          "CONCEPT_CLASS_ID": "PT",
          "INVALID_REASON": "V"
        },
        "includeMapped": false,
        "includeDescendants": true
      }]},
      "name": "Hip fracture",
      "id": 3
    },
    {
      "expression": {"items": [{
        "isExcluded": false,
        "concept": {
          "INVALID_REASON_CAPTION": "Valid",
          "CONCEPT_ID": 36211121,
          "STANDARD_CONCEPT": "C",
          "CONCEPT_CODE": "10049947",
          "VOCABULARY_ID": "MedDRA",
          "CONCEPT_NAME": "Lumbar vertebral fracture",
          "DOMAIN_ID": "Condition",
          "STANDARD_CONCEPT_CAPTION": "Classification",
          "CONCEPT_CLASS_ID": "PT",
          "INVALID_REASON": "V"
        },
        "includeMapped": false,
        "includeDescendants": true
      }]},
      "name": "Spine fracture",
      "id": 4
    },
    {
      "expression": {"items": [{
        "isExcluded": false,
        "concept": {
          "INVALID_REASON_CAPTION": "Valid",
          "CONCEPT_ID": 1516800,
          "STANDARD_CONCEPT": "S",
          "CONCEPT_CODE": "73056",
          "VOCABULARY_ID": "RxNorm",
          "CONCEPT_NAME": "Risedronate",
          "DOMAIN_ID": "Drug",
          "STANDARD_CONCEPT_CAPTION": "Standard",
          "CONCEPT_CLASS_ID": "Ingredient",
          "INVALID_REASON": "V"
        },
        "includeMapped": false,
        "includeDescendants": true
      }]},
      "name": "risedronate\n",
      "id": 5
    }
  ],
  "EndStrategy": {"CustomEra": {
    "DrugCodesetId": 1,
    "GapDays": 60,
    "Offset": 0
  }},
  "cdmVersionRange": ">=5.0.0",
  "CensoringCriteria": [],
  "QualifiedLimit": {"Type": "First"},
  "InclusionRules": [
    {
      "expression": {
        "CriteriaList": [{
          "RestrictVisit": false,
          "StartWindow": {
            "UseEventEnd": false,
            "Start": {
              "Days": null,
              "Coeff": -1
            },
            "End": {
              "Days": null,
              "Coeff": 1
            },
            "UseIndexEnd": false
          },
          "IgnoreObservationPeriod": false,
          "EndWindow": null,
          "Criteria": {"DrugExposure": {
            "OccurrenceEndDate": null,
            "CorrelatedCriteria": null,
            "DrugSourceConcept": null,
            "CodesetId": 2,
            "DrugTypeExclude": false,
            "Quantity": null,
            "DrugType": null,
            "ProviderSpecialty": null,
            "EffectiveDrugDose": null,
            "Gender": null,
            "DaysSupply": null,
            "DoseUnit": null,
            "VisitType": null,
            "Refills": null,
            "First": null,
            "OccurrenceStartDate": null,
            "RouteConcept": null,
            "StopReason": null,
            "LotNumber": null,
            "Age": null
          }},
          "Occurrence": {
            "Type": 1,
            "IsDistinct": false,
            "Count": 0
          }
        }],
        "Type": "ALL",
        "DemographicCriteriaList": [],
        "Groups": [],
        "Count": null
      },
      "name": "No Alendronate",
      "description": null
    },
    {
      "expression": {
        "CriteriaList": [{
          "RestrictVisit": false,
          "StartWindow": {
            "UseEventEnd": false,
            "Start": {
              "Days": null,
              "Coeff": -1
            },
            "End": {
              "Days": 0,
              "Coeff": 1
            },
            "UseIndexEnd": false
          },
          "IgnoreObservationPeriod": false,
          "EndWindow": null,
          "Criteria": {"ConditionOccurrence": {
            "OccurrenceEndDate": null,
            "CorrelatedCriteria": null,
            "ConditionTypeExclude": false,
            "CodesetId": 3,
            "ProviderSpecialty": null,
            "Gender": null,
            "VisitType": null,
            "First": null,
            "OccurrenceStartDate": null,
            "ConditionType": null,
            "ConditionSourceConcept": null,
            "StopReason": null,
            "Age": null
          }},
          "Occurrence": {
            "Type": 1,
            "IsDistinct": false,
            "Count": 0
          }
        }],
        "Type": "ALL",
        "DemographicCriteriaList": [],
        "Groups": [],
        "Count": null
      },
      "name": "No hip fracture",
      "description": null
    },
    {
      "expression": {
        "CriteriaList": [{
          "RestrictVisit": false,
          "StartWindow": {
            "UseEventEnd": false,
            "Start": {
              "Days": null,
              "Coeff": -1
            },
            "End": {
              "Days": 0,
              "Coeff": 1
            },
            "UseIndexEnd": false
          },
          "IgnoreObservationPeriod": false,
          "EndWindow": null,
          "Criteria": {"ConditionOccurrence": {
            "OccurrenceEndDate": null,
            "CorrelatedCriteria": null,
            "ConditionTypeExclude": false,
            "CodesetId": 4,
            "ProviderSpecialty": null,
            "Gender": null,
            "VisitType": null,
            "First": null,
            "OccurrenceStartDate": null,
            "ConditionType": null,
            "ConditionSourceConcept": null,
            "StopReason": null,
            "Age": null
          }},
          "Occurrence": {
            "Type": 1,
            "IsDistinct": false,
            "Count": 0
          }
        }],
        "Type": "ALL",
        "DemographicCriteriaList": [],
        "Groups": [],
        "Count": null
      },
      "name": "No spine fracture",
      "description": null
    },
    {
      "expression": {
        "CriteriaList": [{
          "RestrictVisit": false,
          "StartWindow": {
            "UseEventEnd": false,
            "Start": {
              "Days": null,
              "Coeff": -1
            },
            "End": {
              "Days": null,
              "Coeff": 1
            },
            "UseIndexEnd": false
          },
          "IgnoreObservationPeriod": false,
          "EndWindow": null,
          "Criteria": {"DrugExposure": {
            "OccurrenceEndDate": null,
            "CorrelatedCriteria": null,
            "DrugSourceConcept": null,
            "CodesetId": 5,
            "DrugTypeExclude": false,
            "Quantity": null,
            "DrugType": null,
            "ProviderSpecialty": null,
            "EffectiveDrugDose": null,
            "Gender": null,
            "DaysSupply": null,
            "DoseUnit": null,
            "VisitType": null,
            "Refills": null,
            "First": null,
            "OccurrenceStartDate": null,
            "RouteConcept": null,
            "StopReason": null,
            "LotNumber": null,
            "Age": null
          }},
          "Occurrence": {
            "Type": 1,
            "IsDistinct": false,
            "Count": 0
          }
        }],
        "Type": "ALL",
        "DemographicCriteriaList": [],
        "Groups": [],
        "Count": null
      },
      "name": "No risedronate",
      "description": null
    },
    {
      "expression": {
        "CriteriaList": [{
          "RestrictVisit": false,
          "StartWindow": {
            "UseEventEnd": false,
            "Start": {
              "Days": null,
              "Coeff": -1
            },
            "End": {
              "Days": null,
              "Coeff": 1
            },
            "UseIndexEnd": false
          },
          "IgnoreObservationPeriod": false,
          "EndWindow": null,
          "Criteria": {"ConditionOccurrence": {
            "OccurrenceEndDate": null,
            "CorrelatedCriteria": null,
            "ConditionTypeExclude": false,
            "CodesetId": 0,
            "ProviderSpecialty": null,
            "Gender": null,
            "VisitType": null,
            "First": null,
            "OccurrenceStartDate": null,
            "ConditionType": null,
            "ConditionSourceConcept": null,
            "StopReason": null,
            "Age": null
          }},
          "Occurrence": {
            "Type": 2,
            "IsDistinct": false,
            "Count": 1
          }
        }],
        "Type": "ALL",
        "DemographicCriteriaList": [],
        "Groups": [],
        "Count": null
      },
      "name": "Osteoporosis",
      "description": null
    }
  ],
  "PrimaryCriteria": {
    "CriteriaList": [{"DrugExposure": {
      "OccurrenceEndDate": null,
      "CorrelatedCriteria": null,
      "DrugSourceConcept": null,
      "CodesetId": 1,
      "DrugTypeExclude": false,
      "Quantity": null,
      "DrugType": null,
      "ProviderSpecialty": null,
      "EffectiveDrugDose": null,
      "Gender": null,
      "DaysSupply": null,
      "DoseUnit": null,
      "VisitType": null,
      "Refills": null,
      "First": null,
      "OccurrenceStartDate": null,
      "RouteConcept": null,
      "StopReason": null,
      "LotNumber": null,
      "Age": null
    }}],
    "PrimaryCriteriaLimit": {"Type": "First"},
    "ObservationWindow": {
      "PostDays": 0,
      "PriorDays": 0
    }
  }
}